skill_weather/LICENSE
skill_weather/LICENSE.md
skill_weather/README.md
skill_weather/__init__.py
skill_weather/skill.json
skill_weather/version.py
skill_weather/locale/ca-es/dialog/and.dialog
skill_weather/locale/ca-es/dialog/percentage-number.dialog
skill_weather/locale/ca-es/dialog/condition/clear sky.dialog
skill_weather/locale/ca-es/dialog/condition/clear.dialog
skill_weather/locale/ca-es/dialog/condition/no precipitation expected.dialog
skill_weather/locale/ca-es/dialog/condition/precipitation expected.dialog
skill_weather/locale/ca-es/dialog/condition/rain.dialog
skill_weather/locale/ca-es/dialog/condition/snow.dialog
skill_weather/locale/ca-es/dialog/condition/thunderstorm.dialog
skill_weather/locale/ca-es/dialog/current/current-condition-expected-local.dialog
skill_weather/locale/ca-es/dialog/current/current-condition-expected-location.dialog
skill_weather/locale/ca-es/dialog/current/current-humidity-location.dialog
skill_weather/locale/ca-es/dialog/current/current-temperature-high-local.dialog
skill_weather/locale/ca-es/dialog/current/current-temperature-high-location.dialog
skill_weather/locale/ca-es/dialog/current/current-temperature-high-low.dialog
skill_weather/locale/ca-es/dialog/current/current-temperature-local.dialog
skill_weather/locale/ca-es/dialog/current/current-temperature-location.dialog
skill_weather/locale/ca-es/dialog/current/current-temperature-low-local.dialog
skill_weather/locale/ca-es/dialog/current/current-temperature-low-location.dialog
skill_weather/locale/ca-es/dialog/current/current-weather-local.dialog
skill_weather/locale/ca-es/dialog/current/current-weather-location.dialog
skill_weather/locale/ca-es/dialog/current/current-wind-light-local.dialog
skill_weather/locale/ca-es/dialog/current/current-wind-light-location.dialog
skill_weather/locale/ca-es/dialog/current/current-wind-moderate-local.dialog
skill_weather/locale/ca-es/dialog/current/current-wind-moderate-location.dialog
skill_weather/neon_skill_weather.egg-info/PKG-INFO
skill_weather/neon_skill_weather.egg-info/SOURCES.txt
skill_weather/neon_skill_weather.egg-info/dependency_links.txt
skill_weather/neon_skill_weather.egg-info/entry_points.txt
skill_weather/neon_skill_weather.egg-info/requires.txt
skill_weather/neon_skill_weather.egg-info/top_level.txt
neon_skill_weather-3.1.0.dist-info/LICENSE
neon_skill_weather-3.1.0.dist-info/LICENSE.md
neon_skill_weather-3.1.0.dist-info/METADATA
neon_skill_weather-3.1.0.dist-info/WHEEL
neon_skill_weather-3.1.0.dist-info/entry_points.txt
neon_skill_weather-3.1.0.dist-info/top_level.txt
neon_skill_weather-3.1.0.dist-info/RECORD
