Metadata-Version: 2.1
Name: neon-skill-weather
Version: 3.1.0
Home-page: https://github.com/NeonGeckoCom/skill-weather
Author: Neongecko
Author-email: developers@neon.ai
License: BSD-3-Clause
License-File: LICENSE
License-File: LICENSE.md
Requires-Dist: multi-key-dict==2.0.3
Requires-Dist: requests>=2.13.0
Requires-Dist: neon-utils~=1.9
Requires-Dist: ovos-utils>=0.0.28,~=0.0
Requires-Dist: ovos-workshop~=0.0
Provides-Extra: test
Requires-Dist: neon-minerva[padatious]~=0.3; extra == "test"
